evlib-0.8.7.dist-info/METADATA
evlib-0.8.7.dist-info/WHEEL
evlib-0.8.7.dist-info/licenses/LICENSE.md
evlib/__init__.py
evlib/evlib.cpython-310-darwin.so
evlib/filtering.py
evlib/models/__init__.py
evlib/models/base.py
evlib/models/config.py
evlib/models/e2vid.py
evlib/models/rvt.py
evlib/models/rvt_backbone.py
evlib/models/rvt_layers.py
evlib/models/yolox_blocks.py
evlib/models/yolox_fpn.py
evlib/models/yolox_head.py
evlib/pytorch.py
evlib/representations.py
evlib/simulation/__init__.py
evlib/simulation/config.py
evlib/simulation/esim.py
evlib/simulation/video_processor.py
evlib/visualization.py
evlib-0.8.7.dist-info/RECORD
