Metadata-Version: 2.4
Name: evlib
Version: 0.8.7
Classifier: Environment :: Console
Classifier: Intended Audience :: Science/Research
Classifier: License :: OSI Approved :: MIT License
Classifier: Operating System :: OS Independent
Classifier: Programming Language :: Python
Classifier: Programming Language :: Python :: 3
Classifier: Programming Language :: Python :: 3 :: Only
Classifier: Programming Language :: Python :: 3.10
Classifier: Programming Language :: Python :: 3.11
Classifier: Programming Language :: Python :: 3.12
Classifier: Programming Language :: Rust
Classifier: Topic :: Scientific/Engineering
Classifier: Topic :: Scientific/Engineering :: Image Processing
Classifier: Topic :: Scientific/Engineering :: Artificial Intelligence
Classifier: Typing :: Typed
Requires-Dist: numpy>=1.24.0
Requires-Dist: h5py>=3.8.0 ; sys_platform != 'win32'
Requires-Dist: hdf5plugin>=5.1.0 ; sys_platform != 'win32'
Requires-Dist: polars>=1.30.0
Requires-Dist: pyarrow>=21.0.0
Requires-Dist: pandera[polars]>=0.18.0
Requires-Dist: codecov ; extra == 'dev'
Requires-Dist: maturin ; extra == 'dev'
Requires-Dist: mike>=2.0.0 ; extra == 'dev'
Requires-Dist: mkdocs-material>=9.5.0 ; extra == 'dev'
Requires-Dist: mkdocs-jupyter>=0.24.0 ; extra == 'dev'
Requires-Dist: mkdocs-material[imaging]>=9.5.0 ; extra == 'dev'
Requires-Dist: mypy>=1.0.0 ; extra == 'dev'
Requires-Dist: pygments>=2.18.0 ; extra == 'dev'
Requires-Dist: nbmake ; extra == 'dev'
Requires-Dist: pytest>=7.0.0 ; extra == 'dev'
Requires-Dist: pytest-benchmark ; extra == 'dev'
Requires-Dist: pytest-cov ; extra == 'dev'
Requires-Dist: pytest-markdown-docs>=0.9.0 ; extra == 'dev'
Requires-Dist: pytest-xdist ; extra == 'dev'
Requires-Dist: tqdm>=4.67.1 ; extra == 'dev'
Requires-Dist: twine ; extra == 'dev'
Requires-Dist: duckdb>=1.3.2 ; extra == 'duckdb'
Requires-Dist: jupyter>=1.0.0 ; extra == 'jupyter'
Requires-Dist: matplotlib>=3.7.0 ; extra == 'plot'
Requires-Dist: opencv-python>=4.8.0 ; extra == 'plot'
Requires-Dist: seaborn>=0.13.2 ; extra == 'plot'
Requires-Dist: torch>=2.0.0 ; extra == 'torch'
Requires-Dist: torch>=2.0.0 ; extra == 'pytorch'
Requires-Dist: evlib[dev,duckdb,plot,jupyter,torch,pytorch] ; extra == 'all'
Provides-Extra: dev
Provides-Extra: duckdb
Provides-Extra: jupyter
Provides-Extra: plot
Provides-Extra: torch
Provides-Extra: pytorch
Provides-Extra: all
License-File: LICENSE.md
Summary: Python bindings for event camera utilities
Home-Page: https://github.com/tallamjr/evlib
Author-email: Tarek Allam <t.allam.jr@gmail.com>
Requires-Python: >=3.10
